<?xml version="1.0" encoding="UTF-8" ?>
<PhysicalTable mdsid="m78682e3b-0c20-1000-b5b8-0af502b10000" name="ALL_TAB_COLS" xmlns:xsi="http://www.w3.org/2001/XMLSchema-instance" xmlns="http://www.oracle.com/obis/repository" type="none" maxConn="0" containerRef="/oracle/bi/server/base/Schema/78682d26-0c20-1000-b5b8-0af502b10000.xml#m78682d26-0c20-1000-b5b8-0af502b10000">
<DBMapItem name="DefaultMulDB">
<Value><![CDATA[ALL_TAB_COLS]]></Value>
</DBMapItem>
<PhysicalColumn mdsid="m78682e3c-0c20-1000-b5b8-0af502b10000" name="AVG_COL_LEN" dataType="DOUBLE" precision="15" nullable="true" specialType="none">
</PhysicalColumn>
<PhysicalColumn mdsid="m78682e3d-0c20-1000-b5b8-0af502b10000" name="CHARACTER_SET_NAME" dataType="VARCHAR" precision="44" nullable="true" specialType="none">
</PhysicalColumn>
<PhysicalColumn mdsid="m78682e3e-0c20-1000-b5b8-0af502b10000" name="CHAR_COL_DECL_LENGTH" dataType="DOUBLE" precision="15" nullable="true" specialType="none">
</PhysicalColumn>
<PhysicalColumn mdsid="m78682e3f-0c20-1000-b5b8-0af502b10000" name="CHAR_LENGTH" dataType="DOUBLE" precision="15" nullable="true" specialType="none">
</PhysicalColumn>
<PhysicalColumn mdsid="m78682e40-0c20-1000-b5b8-0af502b10000" name="CHAR_USED" dataType="VARCHAR" precision="1" nullable="true" specialType="none">
</PhysicalColumn>
<PhysicalColumn mdsid="m78682e41-0c20-1000-b5b8-0af502b10000" name="COLUMN_ID" dataType="DOUBLE" precision="15" nullable="true" specialType="none">
</PhysicalColumn>
<PhysicalColumn mdsid="m78682e42-0c20-1000-b5b8-0af502b10000" name="COLUMN_NAME" dataType="VARCHAR" precision="300" specialType="none">
</PhysicalColumn>
<PhysicalColumn mdsid="m78682e43-0c20-1000-b5b8-0af502b10000" name="DATA_DEFAULT" dataType="LONGVARCHAR" precision="4000" nullable="true" specialType="none">
</PhysicalColumn>
<PhysicalColumn mdsid="m78682e44-0c20-1000-b5b8-0af502b10000" name="DATA_LENGTH" dataType="DOUBLE" precision="15" specialType="none">
</PhysicalColumn>
<PhysicalColumn mdsid="m78682e45-0c20-1000-b5b8-0af502b10000" name="DATA_PRECISION" dataType="DOUBLE" precision="15" nullable="true" specialType="none">
</PhysicalColumn>
<PhysicalColumn mdsid="m78682e46-0c20-1000-b5b8-0af502b10000" name="DATA_SCALE" dataType="DOUBLE" precision="15" nullable="true" specialType="none">
</PhysicalColumn>
<PhysicalColumn mdsid="m78682e47-0c20-1000-b5b8-0af502b10000" name="DATA_TYPE" dataType="VARCHAR" precision="106" nullable="true" specialType="none">
</PhysicalColumn>
<PhysicalColumn mdsid="m78682e48-0c20-1000-b5b8-0af502b10000" name="DATA_TYPE_MOD" dataType="VARCHAR" precision="3" nullable="true" specialType="none">
</PhysicalColumn>
<PhysicalColumn mdsid="m78682e49-0c20-1000-b5b8-0af502b10000" name="DATA_TYPE_OWNER" dataType="VARCHAR" precision="30" nullable="true" specialType="none">
</PhysicalColumn>
<PhysicalColumn mdsid="m78682e4a-0c20-1000-b5b8-0af502b10000" name="DATA_UPGRADED" dataType="VARCHAR" precision="3" nullable="true" specialType="none">
</PhysicalColumn>
<PhysicalColumn mdsid="m78682e4b-0c20-1000-b5b8-0af502b10000" name="DEFAULT_LENGTH" dataType="DOUBLE" precision="15" nullable="true" specialType="none">
</PhysicalColumn>
<PhysicalColumn mdsid="m78682e4c-0c20-1000-b5b8-0af502b10000" name="DENSITY" dataType="DOUBLE" precision="15" nullable="true" specialType="none">
</PhysicalColumn>
<PhysicalColumn mdsid="m78682e4d-0c20-1000-b5b8-0af502b10000" name="GLOBAL_STATS" dataType="VARCHAR" precision="3" nullable="true" specialType="none">
</PhysicalColumn>
<PhysicalColumn mdsid="m78682e4e-0c20-1000-b5b8-0af502b10000" name="HIDDEN_COLUMN" dataType="VARCHAR" precision="3" nullable="true" specialType="none">
</PhysicalColumn>
<PhysicalColumn mdsid="m78682e4f-0c20-1000-b5b8-0af502b10000" name="HIGH_VALUE" dataType="VARBINARY" precision="32" nullable="true" specialType="none">
</PhysicalColumn>
<PhysicalColumn mdsid="m78682e50-0c20-1000-b5b8-0af502b10000" name="HISTOGRAM" dataType="VARCHAR" precision="15" nullable="true" specialType="none">
</PhysicalColumn>
<PhysicalColumn mdsid="m78682e51-0c20-1000-b5b8-0af502b10000" name="INTERNAL_COLUMN_ID" dataType="DOUBLE" precision="15" specialType="none">
</PhysicalColumn>
<PhysicalColumn mdsid="m78682e52-0c20-1000-b5b8-0af502b10000" name="LAST_ANALYZED" dataType="DATETIME" nullable="true" specialType="none">
</PhysicalColumn>
<PhysicalColumn mdsid="m78682e53-0c20-1000-b5b8-0af502b10000" name="LOW_VALUE" dataType="VARBINARY" precision="32" nullable="true" specialType="none">
</PhysicalColumn>
<PhysicalColumn mdsid="m78682e54-0c20-1000-b5b8-0af502b10000" name="NULLABLE" dataType="VARCHAR" precision="1" nullable="true" specialType="none">
</PhysicalColumn>
<PhysicalColumn mdsid="m78682e55-0c20-1000-b5b8-0af502b10000" name="NUM_BUCKETS" dataType="DOUBLE" precision="15" nullable="true" specialType="none">
</PhysicalColumn>
<PhysicalColumn mdsid="m78682e56-0c20-1000-b5b8-0af502b10000" name="NUM_DISTINCT" dataType="DOUBLE" precision="15" nullable="true" specialType="none">
</PhysicalColumn>
<PhysicalColumn mdsid="m78682e57-0c20-1000-b5b8-0af502b10000" name="NUM_NULLS" dataType="DOUBLE" precision="15" nullable="true" specialType="none">
</PhysicalColumn>
<PhysicalColumn mdsid="m78682e58-0c20-1000-b5b8-0af502b10000" name="OWNER" dataType="VARCHAR" precision="30" specialType="none">
</PhysicalColumn>
<PhysicalColumn mdsid="m78682e59-0c20-1000-b5b8-0af502b10000" name="QUALIFIED_COL_NAME" dataType="VARCHAR" precision="4000" nullable="true" specialType="none">
</PhysicalColumn>
<PhysicalColumn mdsid="m78682e5a-0c20-1000-b5b8-0af502b10000" name="SAMPLE_SIZE" dataType="DOUBLE" precision="15" nullable="true" specialType="none">
</PhysicalColumn>
<PhysicalColumn mdsid="m78682e5b-0c20-1000-b5b8-0af502b10000" name="SEGMENT_COLUMN_ID" dataType="DOUBLE" precision="15" nullable="true" specialType="none">
</PhysicalColumn>
<PhysicalColumn mdsid="m78682e5c-0c20-1000-b5b8-0af502b10000" name="TABLE_NAME" dataType="VARCHAR" precision="30" specialType="none">
</PhysicalColumn>
<PhysicalColumn mdsid="m78682e5d-0c20-1000-b5b8-0af502b10000" name="USER_STATS" dataType="VARCHAR" precision="3" nullable="true" specialType="none">
</PhysicalColumn>
<PhysicalColumn mdsid="m78682e5e-0c20-1000-b5b8-0af502b10000" name="V80_FMT_IMAGE" dataType="VARCHAR" precision="3" nullable="true" specialType="none">
</PhysicalColumn>
<PhysicalColumn mdsid="m78682e5f-0c20-1000-b5b8-0af502b10000" name="VIRTUAL_COLUMN" dataType="VARCHAR" precision="3" nullable="true" specialType="none">
</PhysicalColumn>
<PhysicalForeignKey mdsid="mb91a7750-0c26-1000-b8db-0af502b10000" name="ALL_TAB_COLS_Foreign Key#5" counterPartKeyRef="/oracle/bi/server/base/PhysicalTable/b8374340-0c26-1000-b8db-0af502b10000.xml#mb90d57f0-0c26-1000-b8db-0af502b10000">
<RefColumns>
<RefColumn refId="mb91a7750-0c26-1000-b8db-0af502b10000-m78682e58-0c20-1000-b5b8-0af502b10000" columnRef="/oracle/bi/server/base/PhysicalTable/78682e3b-0c20-1000-b5b8-0af502b10000.xml#m78682e58-0c20-1000-b5b8-0af502b10000"/>
</RefColumns>
</PhysicalForeignKey>
</PhysicalTable>