<?xml version="1.0" encoding="UTF-8" ?>
<PhysicalTable mdsid="m8b333b24-0c26-1000-9bbc-0af502b10000" name="DBA_HIST_SQLTEXT" xmlns:xsi="http://www.w3.org/2001/XMLSchema-instance" xmlns="http://www.oracle.com/obis/repository" type="none" maxConn="0" containerRef="/oracle/bi/server/base/Schema/8b330ff0-0c26-1000-9bbc-0af502b10000.xml#m8b330ff0-0c26-1000-9bbc-0af502b10000">
<DBMapItem name="DefaultMulDB">
<Value><![CDATA[DBA_HIST_SQLTEXT]]></Value>
</DBMapItem>
<PhysicalColumn mdsid="m8b333b25-0c26-1000-9bbc-0af502b10000" name="COMMAND_TYPE" dataType="DOUBLE" precision="15" nullable="true" specialType="none">
</PhysicalColumn>
<PhysicalColumn mdsid="m8b333b26-0c26-1000-9bbc-0af502b10000" name="DBID" dataType="DOUBLE" precision="15" specialType="none">
</PhysicalColumn>
<PhysicalColumn mdsid="m8b333b27-0c26-1000-9bbc-0af502b10000" name="SQL_ID" dataType="VARCHAR" precision="13" specialType="none">
</PhysicalColumn>
<PhysicalColumn mdsid="m8b333b28-0c26-1000-9bbc-0af502b10000" name="SQL_TEXT" dataType="LONGVARCHAR" precision="4000" nullable="true" specialType="none">
</PhysicalColumn>
</PhysicalTable>