<?xml version="1.0" encoding="UTF-8" ?>
<PhysicalTable mdsid="m8b3337a1-0c26-1000-9bbc-0af502b10000" name="GV_$FILE_HISTOGRAM" xmlns:xsi="http://www.w3.org/2001/XMLSchema-instance" xmlns="http://www.oracle.com/obis/repository" type="none" maxConn="0" containerRef="/oracle/bi/server/base/Schema/8b330ff0-0c26-1000-9bbc-0af502b10000.xml#m8b330ff0-0c26-1000-9bbc-0af502b10000">
<DBMapItem name="DefaultMulDB">
<Value><![CDATA[GV_$FILE_HISTOGRAM]]></Value>
</DBMapItem>
<PhysicalColumn mdsid="m8b3337a2-0c26-1000-9bbc-0af502b10000" name="FILE#" dataType="DOUBLE" precision="15" nullable="true" specialType="none">
</PhysicalColumn>
<PhysicalColumn mdsid="m8b3337a3-0c26-1000-9bbc-0af502b10000" name="INST_ID" dataType="DOUBLE" precision="15" nullable="true" specialType="none">
</PhysicalColumn>
<PhysicalColumn mdsid="m8b3337a4-0c26-1000-9bbc-0af502b10000" name="SINGLEBLKRDS" dataType="DOUBLE" precision="15" nullable="true" specialType="none">
</PhysicalColumn>
<PhysicalColumn mdsid="m8b3337a5-0c26-1000-9bbc-0af502b10000" name="SINGLEBLKRDTIM_MILLI" dataType="DOUBLE" precision="15" nullable="true" specialType="none">
</PhysicalColumn>
</PhysicalTable>